powerplan/__init__.py
powerplan-1.2.0.dist-info/METADATA
powerplan-1.2.0.dist-info/WHEEL
powerplan-1.2.0.dist-info/entry_points.txt
powerplan-1.2.0.dist-info/top_level.txt
powerplan-1.2.0.dist-info/RECORD
