Metadata-Version: 2.4
Name: powerplan
Version: 1.2.0
Summary: Simple Windows-only Python package to read your current power plan (name and GUID) and switch to one of the standard Windows power plans.
Home-page: https://github.com/temal32/powerplan
Author: Temal
Author-email: temal@colinm.de
Classifier: Programming Language :: Python :: 3
Classifier: License :: OSI Approved :: MIT License
Classifier: Operating System :: Microsoft :: Windows
Requires-Python: >=3.0
Dynamic: author
Dynamic: author-email
Dynamic: classifier
Dynamic: description
Dynamic: description-content-type
Dynamic: home-page
Dynamic: requires-python
Dynamic: summary
